typarser/__init__.py
typarser/_base.py
typarser/_base_optarg.py
typarser/_internal_namespace.py
typarser/_native_parser.py
typarser/_removed_component.py
typarser/_version.py
typarser/action.py
typarser/argument.py
typarser/command.py
typarser/errors.py
typarser/flag.py
typarser/namespace.py
typarser/option.py
typarser/parser.py
typarser/shortcuts.py
typarser-1.0.0.dist-info/LICENSE
typarser-1.0.0.dist-info/METADATA
typarser-1.0.0.dist-info/WHEEL
typarser-1.0.0.dist-info/top_level.txt
typarser-1.0.0.dist-info/RECORD
