Metadata-Version: 2.1
Name: typarser
Version: 1.0.0
Summary: Typed argument parser
Home-page: https://github.com/ermishechkin/typarser
Author: Aleksandr Ermishechkin
Author-email: alermishechkin@gmail.com
License: MIT
Platform: any
Classifier: Programming Language :: Python :: 3
Classifier: License :: OSI Approved :: MIT License
Requires-Python: >=3.5
